whichtok/__init__.py
whichtok/graph.py
whichtok/scrape.py
whichtok-0.0.3.dist-info/LICENSE
whichtok-0.0.3.dist-info/METADATA
whichtok-0.0.3.dist-info/WHEEL
whichtok-0.0.3.dist-info/top_level.txt
whichtok-0.0.3.dist-info/RECORD
